lablibpy/__init__.py
lablibpy/knn.py
lablibpy/outliers.py
lablibpy/regression.py
lablibpy-0.1.8.dist-info/licenses/LICENSE
lablibpy-0.1.8.dist-info/METADATA
lablibpy-0.1.8.dist-info/WHEEL
lablibpy-0.1.8.dist-info/top_level.txt
lablibpy-0.1.8.dist-info/RECORD
