Metadata-Version: 2.4
Name: lablibpy
Version: 0.1.8
Summary: Lablibpy is a Python library for data analysis and visualization
Author: Andrew
Author-email: andrewcragg@gmail.com
License-File: LICENSE
Requires-Dist: pandas
Requires-Dist: numpy
Requires-Dist: seaborn
Requires-Dist: matplotlib
Requires-Dist: collections2
Requires-Dist: scikit-learn
Dynamic: author
Dynamic: author-email
Dynamic: license-file
Dynamic: requires-dist
Dynamic: summary
